velar/__init__.py
velar/exceptions.py
velar/group_call_factory.py
velar/group_call_type.py
velar/mtproto_client_type.py
velar/utils.py
velar/dispatcher/__init__.py
velar/dispatcher/action.py
velar/dispatcher/dispatcher.py
velar/dispatcher/dispatcher_mixin.py
velar/implementation/__init__.py
velar/implementation/group_call.py
velar/implementation/group_call_base.py
velar/implementation/group_call_device.py
velar/implementation/group_call_file.py
velar/implementation/group_call_native.py
velar/implementation/group_call_raw.py
velar/mtproto/__init__.py
velar/mtproto/base_bridge.py
velar/mtproto/exceptions.py
velar/mtproto/fipper_bridge.py
velar/mtproto/telethon_bridge.py
velar/mtproto/data/__init__.py
velar/mtproto/data/base_wrapper.py
velar/mtproto/data/group_call_discarded_wrapper.py
velar/mtproto/data/group_call_participant_wrapper.py
velar/mtproto/data/group_call_wrapper.py
velar/mtproto/data/update/__init__.py
velar/mtproto/data/update/update_group_call_participants_wrapper.py
velar/mtproto/data/update/update_group_call_wrapper.py
yins_music-0.1.0.dist-info/LICENSE
yins_music-0.1.0.dist-info/METADATA
yins_music-0.1.0.dist-info/WHEEL
yins_music-0.1.0.dist-info/top_level.txt
yins_music-0.1.0.dist-info/RECORD
