Metadata-Version: 2.1
Name: yins-music
Version: 0.1.0
Summary: a library connecting the tgcalls Python binding with MTProto
Home-page: https://github.com/MarshalX/tgcalls
Author: AyiinXd
Author-email: ayiinxd0307@gmail.com
License: LGPLv3
Project-URL: Documentation, https://tgcalls.org/
Project-URL: Telegram Channel, https://t.me/tgcallslib
Project-URL: Telegram Chat, https://t.me/tgcallschat
Project-URL: Author, https://github.com/AyiinXd
Keywords: python,library,telegram,async,asynchronous,webrtc,lib,voice-chat,voip,group-chat,video-call,calls,fipper,telethon,velar,tgcalls
Classifier: Development Status :: 5 - Production/Stable
Classifier: Natural Language :: English
Classifier: Intended Audience :: Developers
Classifier: License :: OSI Approved :: GNU Lesser General Public License v3 (LGPLv3)
Classifier: Operating System :: OS Independent
Classifier: Operating System :: MacOS
Classifier: Operating System :: Unix
Classifier: Topic :: Internet
Classifier: Topic :: Multimedia
Classifier: Topic :: Multimedia :: Video
Classifier: Topic :: Multimedia :: Video :: Capture
Classifier: Topic :: Multimedia :: Sound/Audio
Classifier: Topic :: Multimedia :: Sound/Audio :: Capture/Recording
Classifier: Topic :: Communications
Classifier: Topic :: Communications :: Internet Phone
Classifier: Topic :: Communications :: Telephony
Classifier: Topic :: Software Development :: Libraries
Classifier: Topic :: Software Development :: Libraries :: Python Modules
Classifier: Programming Language :: Python
Classifier: Programming Language :: Python :: 3
Classifier: Programming Language :: Python :: 3 :: Only
Classifier: Programming Language :: Python :: 3.7
Classifier: Programming Language :: Python :: 3.8
Classifier: Programming Language :: Python :: 3.9
Classifier: Programming Language :: Python :: 3.10
Classifier: Programming Language :: Python :: 3.11
Classifier: Programming Language :: Python :: Implementation
Classifier: Programming Language :: Python :: Implementation :: CPython
Requires-Python: ~=3.7
License-File: LICENSE
Requires-Dist: tgcalls ==3.0.0.dev6
Requires-Dist: av ==10.0.0
Requires-Dist: opencv-python-headless ~=4.5
Provides-Extra: fipper
Requires-Dist: fipper >=0.0.1.dev3 ; extra == 'fipper'
Provides-Extra: telethon
Requires-Dist: telethon >=1.24.0 ; extra == 'telethon'
